django4_recaptcha_admin_login/__init__.py
django4_recaptcha_admin_login/admin.py
django4_recaptcha_admin_login/apps.py
django4_recaptcha_admin_login/forms.py
django4_recaptcha_admin_login/sites.py
django4_recaptcha_admin_login/templates/admin/rechapcha_login.html
django4_recaptcha_admin_login-1.0.dist-info/LICENSE.txt
django4_recaptcha_admin_login-1.0.dist-info/METADATA
django4_recaptcha_admin_login-1.0.dist-info/WHEEL
django4_recaptcha_admin_login-1.0.dist-info/top_level.txt
django4_recaptcha_admin_login-1.0.dist-info/RECORD
