Metadata-Version: 2.1
Name: django4-recaptcha-admin-login
Version: 1.0
Summary: Will add an reCAPTCHA field to Django admin login page to provide a more secure page
Home-page: https://github.com/lseparatio/Django4_reCAPTCHA_admin_login_page
Author: Ionut Zapototchi
Author-email: admin@ionutzapototchi.com
Project-URL: Bug Reports, https://github.com/lseparatio/django4_recaptcha_admin_login/issues
Project-URL: Source, https://github.com/lseparatio/django4_recaptcha_admin_login
Keywords: django,django4,recaptcha,django admin,django login
Classifier: Development Status :: 4 - Beta
Classifier: Intended Audience :: Developers
Classifier: License :: OSI Approved :: MIT License
Classifier: Programming Language :: Python :: 3.10
Classifier: Programming Language :: Python :: 3 :: Only
Requires-Python: >=3.8, <4
License-File: LICENSE.txt
Requires-Dist: django-recaptcha (==3.0.0)
